jupyterhub_sxauthenticator-0.0.4.dist-info/DESCRIPTION.rst
jupyterhub_sxauthenticator-0.0.4.dist-info/METADATA
jupyterhub_sxauthenticator-0.0.4.dist-info/RECORD
jupyterhub_sxauthenticator-0.0.4.dist-info/WHEEL
jupyterhub_sxauthenticator-0.0.4.dist-info/metadata.json
jupyterhub_sxauthenticator-0.0.4.dist-info/top_level.txt
sxauthenticator/__init__.py
