Metadata-Version: 2.0
Name: jupyterhub-sxauthenticator
Version: 0.0.4
Summary: JupyterHub authenticator that hands out temporary accounts for everyone
Home-page: https://github.com/jupyterhub/sxauthenticator
Author: Yuan Xiao
Author-email: yuan.tu.xiao@gmail.com
License: 3 Clause BSD
Platform: UNKNOWN
